{
  "abbr": "Crv",
  "name": "Corvus",
  "stars": [
    {
      "key": "s1",
      "name": "Alchiba",
      "ra": "12:08:24.8",
      "dec": "-24:43:44",
      "mag": 4.02
    },
    {
      "key": "s2",
      "name": "Minkar",
      "ra": "12:10:07.5",
      "dec": "-22:37:11",
      "mag": 3.0
    },
    {
      "key": "s3",
      "name": "Gienah",
      "ra": "12:15:48.4",
      "dec": "-17:32:31",
      "mag": 2.59
    },
    {
      "key": "s4",
      "name": "Algorab",
      "ra": "12:29:51.9",
      "dec": "-16:30:56",
      "mag": 2.95
    },
    {
      "key": "s5",
      "name": "Kraz",
      "ra": "12:34:23.2",
      "dec": "-23:23:48",
      "mag": 2.65
    }
  ],
  "skeleton": [
    {
      "pp": 1,
      "nodes": [
        "s1",
        "s2",
        "s3",
        "s4",
        "s5",
        "s2"
      ]
    }
  ],
  "asterisms": [],
  "art_overlays": []
}